apimaticcalculator/__init__.py
apimaticcalculator/api_helper.py
apimaticcalculator/apimaticcalculator_client.py
apimaticcalculator/configuration.py
apimaticcalculator/decorators.py
apimaticcalculator/controllers/__init__.py
apimaticcalculator/controllers/base_controller.py
apimaticcalculator/controllers/simple_calculator_controller.py
apimaticcalculator/exceptions/__init__.py
apimaticcalculator/exceptions/api_exception.py
apimaticcalculator/http/__init__.py
apimaticcalculator/http/http_call_back.py
apimaticcalculator/http/http_client.py
apimaticcalculator/http/http_method_enum.py
apimaticcalculator/http/http_request.py
apimaticcalculator/http/http_response.py
apimaticcalculator/http/requests_client.py
apimaticcalculator/models/__init__.py
apimaticcalculator/models/operation_type_enum.py
apimaticcalculator/utilities/__init__.py
apimaticcalculator/utilities/file_wrapper.py
absarsnew-1.1.dist-info/LICENSE
absarsnew-1.1.dist-info/METADATA
absarsnew-1.1.dist-info/WHEEL
absarsnew-1.1.dist-info/top_level.txt
absarsnew-1.1.dist-info/RECORD
